openbb_imf/__init__.py
openbb_imf/assets/__init__.py
openbb_imf/assets/imf_country_map.json
openbb_imf/assets/imf_symbols.json
openbb_imf/models/__init__.py
openbb_imf/models/available_indicators.py
openbb_imf/models/direction_of_trade.py
openbb_imf/models/economic_indicators.py
openbb_imf/utils/__init__.py
openbb_imf/utils/constants.py
openbb_imf/utils/dot_helpers.py
openbb_imf/utils/fsi_helpers.py
openbb_imf/utils/helpers.py
openbb_imf/utils/irfcl_helpers.py
openbb_imf-1.1.1.dist-info/METADATA
openbb_imf-1.1.1.dist-info/WHEEL
openbb_imf-1.1.1.dist-info/entry_points.txt
openbb_imf-1.1.1.dist-info/RECORD
